setup.py
distancematrix/__init__.py
distancematrix.egg-info/PKG-INFO
distancematrix.egg-info/SOURCES.txt
distancematrix.egg-info/dependency_links.txt
distancematrix.egg-info/requires.txt
distancematrix.egg-info/top_level.txt