Metadata-Version: 1.0
Name: distancematrix
Version: 0.0.1
Summary: Optimally call distance matrix information for list of origin-dest pairs.
Home-page: http://github.com/axiak/pydistancematrix
Author: Mike Axiak
Author-email: mike@axiak.net
License: BSD
Platform: UNKNOWN
Classifier: Development Status :: 3 - Alpha
Classifier: Operating System :: OS Independent
Classifier: Programming Language :: Python
